knot_pull/__init__.py
knot_pull/bipuller.py
knot_pull/config.py
knot_pull/dowker_code_chiral.py
knot_pull/dowker_code_new.py
knot_pull/downloader.py
knot_pull/finder.py
knot_pull/kpclasses.py
knot_pull/puller.py
knot_pull/reader.py
knot_pull/unentangler.py
knot_pull/vector_ops.py
knot_pull/writer.py
knot_pull/tests/__init__.py
knot_pull/tests/old_t_e_s_t_downloader.py
knot_pull/tests/old_t_e_s_t_reader.py
knot_pull/tests/test_classes.py
knot_pull/tests/test_config.py
knot_pull-0.4.1.data/scripts/knot_pull_check
knot_pull-0.4.1.data/scripts/knot_pull_show
knot_pull-0.4.1.dist-info/LICENSE
knot_pull-0.4.1.dist-info/METADATA
knot_pull-0.4.1.dist-info/WHEEL
knot_pull-0.4.1.dist-info/top_level.txt
knot_pull-0.4.1.dist-info/RECORD
