Metadata-Version: 2.1
Name: knot-pull
Version: 0.4.1
Summary: Simplifier of 3D structures of molecules
Home-page: https://github.com/dzarmola/knot_pull
Author: Aleksandra Jarmolinska
Author-email: dzarmola@gmail.com
License: UNKNOWN
Keywords: protein chromatine topology knot dowker
Platform: UNKNOWN
Classifier: Development Status :: 4 - Beta
Classifier: Programming Language :: Python :: 2
Classifier: Programming Language :: Python :: 2.7
Classifier: Programming Language :: Python :: 3
Classifier: Programming Language :: Python :: 3.2
Classifier: Programming Language :: Python :: 3.3
Classifier: Programming Language :: Python :: 3.4
Classifier: Programming Language :: Python :: 3.5
Classifier: Programming Language :: Python :: 3.6
Classifier: Programming Language :: Python :: 3.7
Classifier: License :: OSI Approved :: GNU General Public License v3 (GPLv3)
Classifier: Operating System :: OS Independent
Requires-Python: >=2.7.*
Requires-Dist: numpy
